{
  "models": 
  [{
    "name": "None",
    "path": "/dev/null"
  },
  {
    "name": "Vangoch",
    "path": "/asdfasdf/vangoch"
  },
  {
    "name": "Kandinski",
    "path": "/asdfasdf/kandinski"
  }
  ],
  "sequence":
  [
    {"name":"Vangoch", "fadeIn": 1, "duration": 20, "strength": 0.5},
    {"name":"Kandinski", "fadeIn": 1, "duration": 20, "strength": 1},
    {"name":"Kandinski", "fadeIn": 1, "duration": 20, "strength": 0.2},
    {"name":"Vangoch", "fadeIn": 1, "duration": 10, "strength": 0.6}
  ]
}