{
  "models": 
  [
  {
    "name": "Fire",
    "path": "../fast-neural-style/mymodels/5_30_8000/fireCropped2.t7"
  },
  {
    "name": "Water",
    "path": "/waterfire"
  },
  {
    "name": "Electricity",
    "path": "/Spacelighting"
  }
  ],
  "sequence":
  [
    {"name":"Fire", "fadeIn": 1, "duration": 5, "strength": 0.5},
    {"name":"Fire", "fadeIn": 1, "duration": 5, "strength": 1},
    {"name":"Fire", "fadeIn": 1, "duration": 5, "strength": 0.2},
    {"name":"Vangoch", "fadeIn": 1, "duration": 5, "strength": 0.6},
    {"name":"Vangoch", "fadeIn": 1, "duration": 5, "strength": 0.6}
  ]
}